{
    "ultimo_aggiornamento": "2026-04-23 20:42:30",
    "fonti": "CoinGecko API (Free Tier)",
    "riepilogo": {
        "segnali_compra": 0,
        "segnali_attendi": 15,
        "segnali_vendi": 0
    },
    "crypto": [
        {
            "id": "solana",
            "nome": "Solana",
            "simbolo": "SOL",
            "logo": "https://coin-images.coingecko.com/coins/images/4128/large/solana.png?1718769756",
            "rank": 7,
            "prezzo": 73.41,
            "variazione_1h": 0.52,
            "variazione_24h": -1.51,
            "variazione_7d": -2.7,
            "volume_24h": 3359947728,
            "rsi_14d": 50.0,
            "analisi_tecnica": {
                "segnale": "ATTENDI",
                "semaforo": "gialla",
                "prezzo_attuale": 73.41,
                "target_price": 77.8146,
                "stop_loss": 69.0054,
                "profitto_netto_stimato_pct": 5.8,
                "fee_stimate_pct": 0.2,
                "rischio": "ALTO"
            }
        },
        {
            "id": "tron",
            "nome": "TRON",
            "simbolo": "TRX",
            "logo": "https://coin-images.coingecko.com/coins/images/1094/large/photo_2026-04-13_09-59-16.png?1776048311",
            "rank": 8,
            "prezzo": 0.281817,
            "variazione_1h": 0.03,
            "variazione_24h": 0.22,
            "variazione_7d": 1.81,
            "volume_24h": 458130252,
            "rsi_14d": 50.0,
            "analisi_tecnica": {
                "segnale": "ATTENDI",
                "semaforo": "gialla",
                "prezzo_attuale": 0.281817,
                "target_price": 0.3001,
                "stop_loss": 0.2635,
                "profitto_netto_stimato_pct": 6.3,
                "fee_stimate_pct": 0.2,
                "rischio": "ALTO"
            }
        },
        {
            "id": "figure-heloc",
            "nome": "Figure Heloc",
            "simbolo": "FIGR_HELOC",
            "logo": "https://coin-images.coingecko.com/coins/images/68480/large/figure.png?1755863954",
            "rank": 9,
            "prezzo": 0.888176,
            "variazione_1h": -0.02,
            "variazione_24h": 1.77,
            "variazione_7d": 1.65,
            "volume_24h": 92103981,
            "rsi_14d": 50.0,
            "analisi_tecnica": {
                "segnale": "ATTENDI",
                "semaforo": "gialla",
                "prezzo_attuale": 0.888176,
                "target_price": 0.9503,
                "stop_loss": 0.826,
                "profitto_netto_stimato_pct": 6.8,
                "fee_stimate_pct": 0.2,
                "rischio": "ALTO"
            }
        },
        {
            "id": "dogecoin",
            "nome": "Dogecoin",
            "simbolo": "DOGE",
            "logo": "https://coin-images.coingecko.com/coins/images/5/large/dogecoin.png?1696501409",
            "rank": 10,
            "prezzo": 0.082834,
            "variazione_1h": 0.63,
            "variazione_24h": 0.51,
            "variazione_7d": -1.63,
            "volume_24h": 1303319409,
            "rsi_14d": 50.0,
            "analisi_tecnica": {
                "segnale": "ATTENDI",
                "semaforo": "gialla",
                "prezzo_attuale": 0.082834,
                "target_price": 0.089,
                "stop_loss": 0.0766,
                "profitto_netto_stimato_pct": 7.3,
                "fee_stimate_pct": 0.2,
                "rischio": "ALTO"
            }
        },
        {
            "id": "hyperliquid",
            "nome": "Hyperliquid",
            "simbolo": "HYPE",
            "logo": "https://coin-images.coingecko.com/coins/images/50882/large/hyperliquid.jpg?1729431300",
            "rank": 13,
            "prezzo": 35.18,
            "variazione_1h": 0.42,
            "variazione_24h": 0.65,
            "variazione_7d": -5.8,
            "volume_24h": 236161201,
            "rsi_14d": 50.0,
            "analisi_tecnica": {
                "segnale": "ATTENDI",
                "semaforo": "gialla",
                "prezzo_attuale": 35.18,
                "target_price": 37.8185,
                "stop_loss": 32.5415,
                "profitto_netto_stimato_pct": 7.3,
                "fee_stimate_pct": 0.2,
                "rischio": "ALTO"
            }
        },
        {
            "id": "cardano",
            "nome": "Cardano",
            "simbolo": "ADA",
            "logo": "https://coin-images.coingecko.com/coins/images/975/large/cardano.png?1696502090",
            "rank": 16,
            "prezzo": 0.212811,
            "variazione_1h": 1.0,
            "variazione_24h": -1.11,
            "variazione_7d": -3.55,
            "volume_24h": 363442301,
            "rsi_14d": 50.0,
            "analisi_tecnica": {
                "segnale": "ATTENDI",
                "semaforo": "gialla",
                "prezzo_attuale": 0.212811,
                "target_price": 0.2288,
                "stop_loss": 0.1969,
                "profitto_netto_stimato_pct": 7.3,
                "fee_stimate_pct": 0.2,
                "rischio": "ALTO"
            }
        },
        {
            "id": "bitcoin-cash",
            "nome": "Bitcoin Cash",
            "simbolo": "BCH",
            "logo": "https://coin-images.coingecko.com/coins/images/780/large/bitcoin-cash-circle.png?1696501932",
            "rank": 15,
            "prezzo": 392.77,
            "variazione_1h": 0.45,
            "variazione_24h": -0.65,
            "variazione_7d": 3.94,
            "volume_24h": 162464383,
            "rsi_14d": 50.0,
            "analisi_tecnica": {
                "segnale": "ATTENDI",
                "semaforo": "gialla",
                "prezzo_attuale": 392.77,
                "target_price": 422.2277,
                "stop_loss": 363.3123,
                "profitto_netto_stimato_pct": 7.3,
                "fee_stimate_pct": 0.2,
                "rischio": "ALTO"
            }
        },
        {
            "id": "monero",
            "nome": "Monero",
            "simbolo": "XMR",
            "logo": "https://coin-images.coingecko.com/coins/images/69/large/monero_logo.png?1696501460",
            "rank": 17,
            "prezzo": 320.3,
            "variazione_1h": 0.47,
            "variazione_24h": -1.02,
            "variazione_7d": 8.7,
            "volume_24h": 116098498,
            "rsi_14d": 50.0,
            "analisi_tecnica": {
                "segnale": "ATTENDI",
                "semaforo": "gialla",
                "prezzo_attuale": 320.3,
                "target_price": 344.3225,
                "stop_loss": 296.2775,
                "profitto_netto_stimato_pct": 7.3,
                "fee_stimate_pct": 0.2,
                "rischio": "ALTO"
            }
        },
        {
            "id": "chainlink",
            "nome": "Chainlink",
            "simbolo": "LINK",
            "logo": "https://coin-images.coingecko.com/coins/images/877/large/Chainlink_Logo_500.png?1760023405",
            "rank": 18,
            "prezzo": 7.97,
            "variazione_1h": 0.53,
            "variazione_24h": -0.67,
            "variazione_7d": -2.63,
            "volume_24h": 259468729,
            "rsi_14d": 50.0,
            "analisi_tecnica": {
                "segnale": "ATTENDI",
                "semaforo": "gialla",
                "prezzo_attuale": 7.97,
                "target_price": 8.5678,
                "stop_loss": 7.3723,
                "profitto_netto_stimato_pct": 7.3,
                "fee_stimate_pct": 0.2,
                "rischio": "ALTO"
            }
        },
        {
            "id": "stellar",
            "nome": "Stellar",
            "simbolo": "XLM",
            "logo": "https://coin-images.coingecko.com/coins/images/100/large/fmpFRHHQ_400x400.jpg?1735231350",
            "rank": 19,
            "prezzo": 0.150331,
            "variazione_1h": 0.03,
            "variazione_24h": -1.66,
            "variazione_7d": 5.67,
            "volume_24h": 103140740,
            "rsi_14d": 50.0,
            "analisi_tecnica": {
                "segnale": "ATTENDI",
                "semaforo": "gialla",
                "prezzo_attuale": 0.150331,
                "target_price": 0.1616,
                "stop_loss": 0.1391,
                "profitto_netto_stimato_pct": 7.3,
                "fee_stimate_pct": 0.2,
                "rischio": "ALTO"
            }
        },
        {
            "id": "canton-network",
            "nome": "Canton",
            "simbolo": "CC",
            "logo": "https://coin-images.coingecko.com/coins/images/70468/large/Canton-Ticker_%281%29.png?1762826299",
            "rank": 20,
            "prezzo": 0.127938,
            "variazione_1h": -0.28,
            "variazione_24h": -1.91,
            "variazione_7d": 0.96,
            "volume_24h": 6891335,
            "rsi_14d": 50.0,
            "analisi_tecnica": {
                "segnale": "ATTENDI",
                "semaforo": "gialla",
                "prezzo_attuale": 0.127938,
                "target_price": 0.1375,
                "stop_loss": 0.1183,
                "profitto_netto_stimato_pct": 7.3,
                "fee_stimate_pct": 0.2,
                "rischio": "ALTO"
            }
        },
        {
            "id": "ethereum",
            "nome": "Ethereum",
            "simbolo": "ETH",
            "logo": "https://coin-images.coingecko.com/coins/images/279/large/ethereum.png?1696501628",
            "rank": 2,
            "prezzo": 1991.02,
            "variazione_1h": 0.66,
            "variazione_24h": -2.7,
            "variazione_7d": 0.12,
            "volume_24h": 16169441106,
            "rsi_14d": 58.48,
            "analisi_tecnica": {
                "segnale": "ATTENDI",
                "semaforo": "gialla",
                "prezzo_attuale": 1991.02,
                "target_price": 2060.7057,
                "stop_loss": 1921.3343,
                "profitto_netto_stimato_pct": 3.3,
                "fee_stimate_pct": 0.2,
                "rischio": "MEDIO"
            }
        },
        {
            "id": "ripple",
            "nome": "XRP",
            "simbolo": "XRP",
            "logo": "https://coin-images.coingecko.com/coins/images/44/large/xrp-symbol-white-128.png?1696501442",
            "rank": 4,
            "prezzo": 1.23,
            "variazione_1h": 0.41,
            "variazione_24h": 0.03,
            "variazione_7d": -0.9,
            "volume_24h": 2298334595,
            "rsi_14d": 63.82,
            "analisi_tecnica": {
                "segnale": "ATTENDI",
                "semaforo": "gialla",
                "prezzo_attuale": 1.23,
                "target_price": 1.2853,
                "stop_loss": 1.1746,
                "profitto_netto_stimato_pct": 4.3,
                "fee_stimate_pct": 0.2,
                "rischio": "MEDIO"
            }
        },
        {
            "id": "binancecoin",
            "nome": "BNB",
            "simbolo": "BNB",
            "logo": "https://coin-images.coingecko.com/coins/images/825/large/bnb-icon2_2x.png?1696501970",
            "rank": 5,
            "prezzo": 545.67,
            "variazione_1h": 0.35,
            "variazione_24h": -0.46,
            "variazione_7d": 1.06,
            "volume_24h": 919810262,
            "rsi_14d": 65.37,
            "analisi_tecnica": {
                "segnale": "ATTENDI",
                "semaforo": "gialla",
                "prezzo_attuale": 545.67,
                "target_price": 572.9535,
                "stop_loss": 518.3865,
                "profitto_netto_stimato_pct": 4.8,
                "fee_stimate_pct": 0.2,
                "rischio": "MEDIO"
            }
        },
        {
            "id": "bitcoin",
            "nome": "Bitcoin",
            "simbolo": "BTC",
            "logo": "https://coin-images.coingecko.com/coins/images/1/large/bitcoin.png?1696501400",
            "rank": 1,
            "prezzo": 66749,
            "variazione_1h": 0.37,
            "variazione_24h": -0.52,
            "variazione_7d": 4.31,
            "volume_24h": 37472513408,
            "rsi_14d": 67.96,
            "analisi_tecnica": {
                "segnale": "ATTENDI",
                "semaforo": "gialla",
                "prezzo_attuale": 66749,
                "target_price": 68751.47,
                "stop_loss": 64746.53,
                "profitto_netto_stimato_pct": 2.8,
                "fee_stimate_pct": 0.2,
                "rischio": "MEDIO"
            }
        }
    ]
}