{
    "ultimo_aggiornamento": "2026-04-24 21:37:44",
    "fonti": "CoinGecko API (Free Tier)",
    "riepilogo": {
        "segnali_compra": 0,
        "segnali_attendi": 15,
        "segnali_vendi": 0
    },
    "crypto": [
        {
            "id": "solana",
            "nome": "Solana",
            "simbolo": "SOL",
            "logo": "https://coin-images.coingecko.com/coins/images/4128/large/solana.png?1718769756",
            "rank": 7,
            "prezzo": 73.82,
            "variazione_1h": -0.05,
            "variazione_24h": 0.45,
            "variazione_7d": -2.75,
            "volume_24h": 2589295199,
            "rsi_14d": 50.0,
            "analisi_tecnica": {
                "segnale": "ATTENDI",
                "semaforo": "gialla",
                "prezzo_attuale": 73.82,
                "target_price": 78.2492,
                "stop_loss": 69.3908,
                "profitto_netto_stimato_pct": 5.8,
                "fee_stimate_pct": 0.2,
                "rischio": "ALTO"
            }
        },
        {
            "id": "tron",
            "nome": "TRON",
            "simbolo": "TRX",
            "logo": "https://coin-images.coingecko.com/coins/images/1094/large/photo_2026-04-13_09-59-16.png?1776048311",
            "rank": 8,
            "prezzo": 0.276203,
            "variazione_1h": -0.21,
            "variazione_24h": -2.0,
            "variazione_7d": -0.62,
            "volume_24h": 540783857,
            "rsi_14d": 50.0,
            "analisi_tecnica": {
                "segnale": "ATTENDI",
                "semaforo": "gialla",
                "prezzo_attuale": 0.276203,
                "target_price": 0.2942,
                "stop_loss": 0.2582,
                "profitto_netto_stimato_pct": 6.3,
                "fee_stimate_pct": 0.2,
                "rischio": "ALTO"
            }
        },
        {
            "id": "figure-heloc",
            "nome": "Figure Heloc",
            "simbolo": "FIGR_HELOC",
            "logo": "https://coin-images.coingecko.com/coins/images/68480/large/figure.png?1755863954",
            "rank": 9,
            "prezzo": 0.885529,
            "variazione_1h": -0.03,
            "variazione_24h": -0.28,
            "variazione_7d": 0.79,
            "volume_24h": 266330292,
            "rsi_14d": 50.0,
            "analisi_tecnica": {
                "segnale": "ATTENDI",
                "semaforo": "gialla",
                "prezzo_attuale": 0.885529,
                "target_price": 0.9475,
                "stop_loss": 0.8235,
                "profitto_netto_stimato_pct": 6.8,
                "fee_stimate_pct": 0.2,
                "rischio": "ALTO"
            }
        },
        {
            "id": "dogecoin",
            "nome": "Dogecoin",
            "simbolo": "DOGE",
            "logo": "https://coin-images.coingecko.com/coins/images/5/large/dogecoin.png?1696501409",
            "rank": 10,
            "prezzo": 0.084349,
            "variazione_1h": 0.55,
            "variazione_24h": 1.63,
            "variazione_7d": -0.79,
            "volume_24h": 1274842961,
            "rsi_14d": 50.0,
            "analisi_tecnica": {
                "segnale": "ATTENDI",
                "semaforo": "gialla",
                "prezzo_attuale": 0.084349,
                "target_price": 0.0907,
                "stop_loss": 0.078,
                "profitto_netto_stimato_pct": 7.3,
                "fee_stimate_pct": 0.2,
                "rischio": "ALTO"
            }
        },
        {
            "id": "hyperliquid",
            "nome": "Hyperliquid",
            "simbolo": "HYPE",
            "logo": "https://coin-images.coingecko.com/coins/images/50882/large/hyperliquid.jpg?1729431300",
            "rank": 13,
            "prezzo": 35.27,
            "variazione_1h": -0.17,
            "variazione_24h": -0.14,
            "variazione_7d": -6.83,
            "volume_24h": 160281887,
            "rsi_14d": 50.0,
            "analisi_tecnica": {
                "segnale": "ATTENDI",
                "semaforo": "gialla",
                "prezzo_attuale": 35.27,
                "target_price": 37.9153,
                "stop_loss": 32.6248,
                "profitto_netto_stimato_pct": 7.3,
                "fee_stimate_pct": 0.2,
                "rischio": "ALTO"
            }
        },
        {
            "id": "cardano",
            "nome": "Cardano",
            "simbolo": "ADA",
            "logo": "https://coin-images.coingecko.com/coins/images/975/large/cardano.png?1696502090",
            "rank": 15,
            "prezzo": 0.214821,
            "variazione_1h": 0.19,
            "variazione_24h": 0.81,
            "variazione_7d": -2.91,
            "volume_24h": 256418581,
            "rsi_14d": 50.0,
            "analisi_tecnica": {
                "segnale": "ATTENDI",
                "semaforo": "gialla",
                "prezzo_attuale": 0.214821,
                "target_price": 0.2309,
                "stop_loss": 0.1987,
                "profitto_netto_stimato_pct": 7.3,
                "fee_stimate_pct": 0.2,
                "rischio": "ALTO"
            }
        },
        {
            "id": "bitcoin-cash",
            "nome": "Bitcoin Cash",
            "simbolo": "BCH",
            "logo": "https://coin-images.coingecko.com/coins/images/780/large/bitcoin-cash-circle.png?1696501932",
            "rank": 16,
            "prezzo": 389.79,
            "variazione_1h": -0.04,
            "variazione_24h": -0.6,
            "variazione_7d": 1.01,
            "volume_24h": 130314710,
            "rsi_14d": 50.0,
            "analisi_tecnica": {
                "segnale": "ATTENDI",
                "semaforo": "gialla",
                "prezzo_attuale": 389.79,
                "target_price": 419.0242,
                "stop_loss": 360.5558,
                "profitto_netto_stimato_pct": 7.3,
                "fee_stimate_pct": 0.2,
                "rischio": "ALTO"
            }
        },
        {
            "id": "chainlink",
            "nome": "Chainlink",
            "simbolo": "LINK",
            "logo": "https://coin-images.coingecko.com/coins/images/877/large/Chainlink_Logo_500.png?1760023405",
            "rank": 17,
            "prezzo": 8.02,
            "variazione_1h": -0.22,
            "variazione_24h": 0.55,
            "variazione_7d": -2.49,
            "volume_24h": 186844526,
            "rsi_14d": 50.0,
            "analisi_tecnica": {
                "segnale": "ATTENDI",
                "semaforo": "gialla",
                "prezzo_attuale": 8.02,
                "target_price": 8.6215,
                "stop_loss": 7.4185,
                "profitto_netto_stimato_pct": 7.3,
                "fee_stimate_pct": 0.2,
                "rischio": "ALTO"
            }
        },
        {
            "id": "monero",
            "nome": "Monero",
            "simbolo": "XMR",
            "logo": "https://coin-images.coingecko.com/coins/images/69/large/monero_logo.png?1696501460",
            "rank": 18,
            "prezzo": 314.43,
            "variazione_1h": 0.09,
            "variazione_24h": -2.16,
            "variazione_7d": 6.11,
            "volume_24h": 99198146,
            "rsi_14d": 50.0,
            "analisi_tecnica": {
                "segnale": "ATTENDI",
                "semaforo": "gialla",
                "prezzo_attuale": 314.43,
                "target_price": 338.0122,
                "stop_loss": 290.8478,
                "profitto_netto_stimato_pct": 7.3,
                "fee_stimate_pct": 0.2,
                "rischio": "ALTO"
            }
        },
        {
            "id": "zcash",
            "nome": "Zcash",
            "simbolo": "ZEC",
            "logo": "https://coin-images.coingecko.com/coins/images/486/large/circle-zcash-color.png?1696501740",
            "rank": 19,
            "prezzo": 307.13,
            "variazione_1h": 0.12,
            "variazione_24h": 3.22,
            "variazione_7d": 9.19,
            "volume_24h": 457284969,
            "rsi_14d": 50.0,
            "analisi_tecnica": {
                "segnale": "ATTENDI",
                "semaforo": "gialla",
                "prezzo_attuale": 307.13,
                "target_price": 330.1647,
                "stop_loss": 284.0953,
                "profitto_netto_stimato_pct": 7.3,
                "fee_stimate_pct": 0.2,
                "rischio": "ALTO"
            }
        },
        {
            "id": "canton-network",
            "nome": "Canton",
            "simbolo": "CC",
            "logo": "https://coin-images.coingecko.com/coins/images/70468/large/Canton-Ticker_%281%29.png?1762826299",
            "rank": 20,
            "prezzo": 0.129262,
            "variazione_1h": -0.73,
            "variazione_24h": 0.9,
            "variazione_7d": 0.49,
            "volume_24h": 7053176,
            "rsi_14d": 50.0,
            "analisi_tecnica": {
                "segnale": "ATTENDI",
                "semaforo": "gialla",
                "prezzo_attuale": 0.129262,
                "target_price": 0.139,
                "stop_loss": 0.1196,
                "profitto_netto_stimato_pct": 7.3,
                "fee_stimate_pct": 0.2,
                "rischio": "ALTO"
            }
        },
        {
            "id": "ethereum",
            "nome": "Ethereum",
            "simbolo": "ETH",
            "logo": "https://coin-images.coingecko.com/coins/images/279/large/ethereum.png?1696501628",
            "rank": 2,
            "prezzo": 1975.49,
            "variazione_1h": -0.41,
            "variazione_24h": -0.83,
            "variazione_7d": -4.37,
            "volume_24h": 11111904489,
            "rsi_14d": 54.58,
            "analisi_tecnica": {
                "segnale": "ATTENDI",
                "semaforo": "gialla",
                "prezzo_attuale": 1975.49,
                "target_price": 2044.6321,
                "stop_loss": 1906.3478,
                "profitto_netto_stimato_pct": 3.3,
                "fee_stimate_pct": 0.2,
                "rischio": "MEDIO"
            }
        },
        {
            "id": "ripple",
            "nome": "XRP",
            "simbolo": "XRP",
            "logo": "https://coin-images.coingecko.com/coins/images/44/large/xrp-symbol-white-128.png?1696501442",
            "rank": 4,
            "prezzo": 1.23,
            "variazione_1h": 0.06,
            "variazione_24h": -0.12,
            "variazione_7d": -2.55,
            "volume_24h": 1879188938,
            "rsi_14d": 62.34,
            "analisi_tecnica": {
                "segnale": "ATTENDI",
                "semaforo": "gialla",
                "prezzo_attuale": 1.23,
                "target_price": 1.2853,
                "stop_loss": 1.1746,
                "profitto_netto_stimato_pct": 4.3,
                "fee_stimate_pct": 0.2,
                "rischio": "MEDIO"
            }
        },
        {
            "id": "bitcoin",
            "nome": "Bitcoin",
            "simbolo": "BTC",
            "logo": "https://coin-images.coingecko.com/coins/images/1/large/bitcoin.png?1696501400",
            "rank": 1,
            "prezzo": 66193,
            "variazione_1h": -0.11,
            "variazione_24h": -0.87,
            "variazione_7d": 0.59,
            "volume_24h": 28233189776,
            "rsi_14d": 63.24,
            "analisi_tecnica": {
                "segnale": "ATTENDI",
                "semaforo": "gialla",
                "prezzo_attuale": 66193,
                "target_price": 68178.79,
                "stop_loss": 64207.21,
                "profitto_netto_stimato_pct": 2.8,
                "fee_stimate_pct": 0.2,
                "rischio": "MEDIO"
            }
        },
        {
            "id": "binancecoin",
            "nome": "BNB",
            "simbolo": "BNB",
            "logo": "https://coin-images.coingecko.com/coins/images/825/large/bnb-icon2_2x.png?1696501970",
            "rank": 5,
            "prezzo": 543.68,
            "variazione_1h": -0.17,
            "variazione_24h": -0.52,
            "variazione_7d": -0.22,
            "volume_24h": 735248761,
            "rsi_14d": 63.35,
            "analisi_tecnica": {
                "segnale": "ATTENDI",
                "semaforo": "gialla",
                "prezzo_attuale": 543.68,
                "target_price": 570.864,
                "stop_loss": 516.496,
                "profitto_netto_stimato_pct": 4.8,
                "fee_stimate_pct": 0.2,
                "rischio": "MEDIO"
            }
        }
    ]
}