{
    "ultimo_aggiornamento": "2026-04-18 07:38:42",
    "fonti": "CoinGecko API (Free Tier)",
    "riepilogo": {
        "segnali_compra": 0,
        "segnali_attendi": 12,
        "segnali_vendi": 3
    },
    "crypto": [
        {
            "id": "solana",
            "nome": "Solana",
            "simbolo": "SOL",
            "logo": "https://coin-images.coingecko.com/coins/images/4128/large/solana.png?1718769756",
            "rank": 7,
            "prezzo": 75.18,
            "variazione_1h": 0.0,
            "variazione_24h": 0.46,
            "variazione_7d": 4.8,
            "volume_24h": 4493209202,
            "rsi_14d": 50.0,
            "analisi_tecnica": {
                "segnale": "ATTENDI",
                "semaforo": "gialla",
                "prezzo_attuale": 75.18,
                "target_price": 79.6908,
                "stop_loss": 70.6692,
                "profitto_netto_stimato_pct": 5.8,
                "fee_stimate_pct": 0.2,
                "rischio": "ALTO"
            }
        },
        {
            "id": "tron",
            "nome": "TRON",
            "simbolo": "TRX",
            "logo": "https://coin-images.coingecko.com/coins/images/1094/large/photo_2026-04-13_09-59-16.png?1776048311",
            "rank": 8,
            "prezzo": 0.277802,
            "variazione_1h": -0.11,
            "variazione_24h": 0.45,
            "variazione_7d": 2.16,
            "volume_24h": 489135330,
            "rsi_14d": 50.0,
            "analisi_tecnica": {
                "segnale": "ATTENDI",
                "semaforo": "gialla",
                "prezzo_attuale": 0.277802,
                "target_price": 0.2959,
                "stop_loss": 0.2597,
                "profitto_netto_stimato_pct": 6.3,
                "fee_stimate_pct": 0.2,
                "rischio": "ALTO"
            }
        },
        {
            "id": "figure-heloc",
            "nome": "Figure Heloc",
            "simbolo": "FIGR_HELOC",
            "logo": "https://coin-images.coingecko.com/coins/images/68480/large/figure.png?1755863954",
            "rank": 9,
            "prezzo": 0.867627,
            "variazione_1h": 0.0,
            "variazione_24h": -1.16,
            "variazione_7d": -0.35,
            "volume_24h": 24808678,
            "rsi_14d": 50.0,
            "analisi_tecnica": {
                "segnale": "ATTENDI",
                "semaforo": "gialla",
                "prezzo_attuale": 0.867627,
                "target_price": 0.9284,
                "stop_loss": 0.8069,
                "profitto_netto_stimato_pct": 6.8,
                "fee_stimate_pct": 0.2,
                "rischio": "ALTO"
            }
        },
        {
            "id": "dogecoin",
            "nome": "Dogecoin",
            "simbolo": "DOGE",
            "logo": "https://coin-images.coingecko.com/coins/images/5/large/dogecoin.png?1696501409",
            "rank": 10,
            "prezzo": 0.084079,
            "variazione_1h": 0.17,
            "variazione_24h": 1.02,
            "variazione_7d": 6.22,
            "volume_24h": 1941055103,
            "rsi_14d": 50.0,
            "analisi_tecnica": {
                "segnale": "ATTENDI",
                "semaforo": "gialla",
                "prezzo_attuale": 0.084079,
                "target_price": 0.0904,
                "stop_loss": 0.0778,
                "profitto_netto_stimato_pct": 7.3,
                "fee_stimate_pct": 0.2,
                "rischio": "ALTO"
            }
        },
        {
            "id": "hyperliquid",
            "nome": "Hyperliquid",
            "simbolo": "HYPE",
            "logo": "https://coin-images.coingecko.com/coins/images/50882/large/hyperliquid.jpg?1729431300",
            "rank": 13,
            "prezzo": 37.98,
            "variazione_1h": -0.34,
            "variazione_24h": 2.73,
            "variazione_7d": 6.16,
            "volume_24h": 267602831,
            "rsi_14d": 50.0,
            "analisi_tecnica": {
                "segnale": "ATTENDI",
                "semaforo": "gialla",
                "prezzo_attuale": 37.98,
                "target_price": 40.8285,
                "stop_loss": 35.1315,
                "profitto_netto_stimato_pct": 7.3,
                "fee_stimate_pct": 0.2,
                "rischio": "ALTO"
            }
        },
        {
            "id": "cardano",
            "nome": "Cardano",
            "simbolo": "ADA",
            "logo": "https://coin-images.coingecko.com/coins/images/975/large/cardano.png?1696502090",
            "rank": 14,
            "prezzo": 0.219601,
            "variazione_1h": 0.24,
            "variazione_24h": 1.15,
            "variazione_7d": 2.69,
            "volume_24h": 484680217,
            "rsi_14d": 50.0,
            "analisi_tecnica": {
                "segnale": "ATTENDI",
                "semaforo": "gialla",
                "prezzo_attuale": 0.219601,
                "target_price": 0.2361,
                "stop_loss": 0.2031,
                "profitto_netto_stimato_pct": 7.3,
                "fee_stimate_pct": 0.2,
                "rischio": "ALTO"
            }
        },
        {
            "id": "bitcoin-cash",
            "nome": "Bitcoin Cash",
            "simbolo": "BCH",
            "logo": "https://coin-images.coingecko.com/coins/images/780/large/bitcoin-cash-circle.png?1696501932",
            "rank": 16,
            "prezzo": 385.9,
            "variazione_1h": 0.16,
            "variazione_24h": 1.25,
            "variazione_7d": 2.81,
            "volume_24h": 189919295,
            "rsi_14d": 50.0,
            "analisi_tecnica": {
                "segnale": "ATTENDI",
                "semaforo": "gialla",
                "prezzo_attuale": 385.9,
                "target_price": 414.8425,
                "stop_loss": 356.9575,
                "profitto_netto_stimato_pct": 7.3,
                "fee_stimate_pct": 0.2,
                "rischio": "ALTO"
            }
        },
        {
            "id": "memecore",
            "nome": "MemeCore",
            "simbolo": "M",
            "logo": "https://coin-images.coingecko.com/coins/images/53247/large/square-bg-transparent.png?1752637478",
            "rank": 17,
            "prezzo": 3.74,
            "variazione_1h": -0.83,
            "variazione_24h": 15.93,
            "variazione_7d": 58.63,
            "volume_24h": 23674040,
            "rsi_14d": 50.0,
            "analisi_tecnica": {
                "segnale": "ATTENDI",
                "semaforo": "gialla",
                "prezzo_attuale": 3.74,
                "target_price": 4.0205,
                "stop_loss": 3.4595,
                "profitto_netto_stimato_pct": 7.3,
                "fee_stimate_pct": 0.2,
                "rischio": "ALTO"
            }
        },
        {
            "id": "chainlink",
            "nome": "Chainlink",
            "simbolo": "LINK",
            "logo": "https://coin-images.coingecko.com/coins/images/877/large/Chainlink_Logo_500.png?1760023405",
            "rank": 18,
            "prezzo": 8.17,
            "variazione_1h": 0.03,
            "variazione_24h": 1.9,
            "variazione_7d": 6.59,
            "volume_24h": 319967612,
            "rsi_14d": 50.0,
            "analisi_tecnica": {
                "segnale": "ATTENDI",
                "semaforo": "gialla",
                "prezzo_attuale": 8.17,
                "target_price": 8.7828,
                "stop_loss": 7.5573,
                "profitto_netto_stimato_pct": 7.3,
                "fee_stimate_pct": 0.2,
                "rischio": "ALTO"
            }
        },
        {
            "id": "ravedao",
            "nome": "RaveDAO",
            "simbolo": "RAVE",
            "logo": "https://coin-images.coingecko.com/coins/images/70544/large/coin.jpeg?1762452940",
            "rank": 19,
            "prezzo": 22.62,
            "variazione_1h": -1.79,
            "variazione_24h": 43.36,
            "variazione_7d": 1161.57,
            "volume_24h": 281794587,
            "rsi_14d": 50.0,
            "analisi_tecnica": {
                "segnale": "ATTENDI",
                "semaforo": "gialla",
                "prezzo_attuale": 22.62,
                "target_price": 24.3165,
                "stop_loss": 20.9235,
                "profitto_netto_stimato_pct": 7.3,
                "fee_stimate_pct": 0.2,
                "rischio": "ALTO"
            }
        },
        {
            "id": "monero",
            "nome": "Monero",
            "simbolo": "XMR",
            "logo": "https://coin-images.coingecko.com/coins/images/69/large/monero_logo.png?1696501460",
            "rank": 20,
            "prezzo": 294.37,
            "variazione_1h": 0.06,
            "variazione_24h": -0.53,
            "variazione_7d": 2.87,
            "volume_24h": 110679522,
            "rsi_14d": 50.0,
            "analisi_tecnica": {
                "segnale": "ATTENDI",
                "semaforo": "gialla",
                "prezzo_attuale": 294.37,
                "target_price": 316.4477,
                "stop_loss": 272.2923,
                "profitto_netto_stimato_pct": 7.3,
                "fee_stimate_pct": 0.2,
                "rischio": "ALTO"
            }
        },
        {
            "id": "binancecoin",
            "nome": "BNB",
            "simbolo": "BNB",
            "logo": "https://coin-images.coingecko.com/coins/images/825/large/bnb-icon2_2x.png?1696501970",
            "rank": 5,
            "prezzo": 547.17,
            "variazione_1h": -0.04,
            "variazione_24h": 2.61,
            "variazione_7d": 5.83,
            "volume_24h": 1269429032,
            "rsi_14d": 67.18,
            "analisi_tecnica": {
                "segnale": "ATTENDI",
                "semaforo": "gialla",
                "prezzo_attuale": 547.17,
                "target_price": 574.5285,
                "stop_loss": 519.8115,
                "profitto_netto_stimato_pct": 4.8,
                "fee_stimate_pct": 0.2,
                "rischio": "MEDIO"
            }
        },
        {
            "id": "ethereum",
            "nome": "Ethereum",
            "simbolo": "ETH",
            "logo": "https://coin-images.coingecko.com/coins/images/279/large/ethereum.png?1696501628",
            "rank": 2,
            "prezzo": 2044.36,
            "variazione_1h": -0.16,
            "variazione_24h": 3.07,
            "variazione_7d": 7.2,
            "volume_24h": 20879800229,
            "rsi_14d": 70.09,
            "analisi_tecnica": {
                "segnale": "VENDI",
                "semaforo": "rossa",
                "prezzo_attuale": 2044.36,
                "target_price": 1901.2548,
                "stop_loss": 2115.9126,
                "profitto_netto_stimato_pct": 6.8,
                "fee_stimate_pct": 0.2,
                "rischio": "MEDIO"
            }
        },
        {
            "id": "ripple",
            "nome": "XRP",
            "simbolo": "XRP",
            "logo": "https://coin-images.coingecko.com/coins/images/44/large/xrp-symbol-white-128.png?1696501442",
            "rank": 4,
            "prezzo": 1.25,
            "variazione_1h": 0.55,
            "variazione_24h": 2.58,
            "variazione_7d": 9.06,
            "volume_24h": 3192193801,
            "rsi_14d": 71.15,
            "analisi_tecnica": {
                "segnale": "VENDI",
                "semaforo": "rossa",
                "prezzo_attuale": 1.25,
                "target_price": 1.1375,
                "stop_loss": 1.3062,
                "profitto_netto_stimato_pct": 8.8,
                "fee_stimate_pct": 0.2,
                "rischio": "MEDIO"
            }
        },
        {
            "id": "bitcoin",
            "nome": "Bitcoin",
            "simbolo": "BTC",
            "logo": "https://coin-images.coingecko.com/coins/images/1/large/bitcoin.png?1696501400",
            "rank": 1,
            "prezzo": 65472,
            "variazione_1h": -0.07,
            "variazione_24h": 2.85,
            "variazione_7d": 5.5,
            "volume_24h": 60710036991,
            "rsi_14d": 76.75,
            "analisi_tecnica": {
                "segnale": "VENDI",
                "semaforo": "rossa",
                "prezzo_attuale": 65472,
                "target_price": 61543.68,
                "stop_loss": 67436.16,
                "profitto_netto_stimato_pct": 5.8,
                "fee_stimate_pct": 0.2,
                "rischio": "MEDIO"
            }
        }
    ]
}